ai_model_registry/__init__.py
ai_model_registry-0.1.0.dist-info/METADATA
ai_model_registry-0.1.0.dist-info/WHEEL
ai_model_registry-0.1.0.dist-info/RECORD
