Metadata-Version: 2.4
Name: ai-model-registry
Version: 0.1.0
Summary: Single source of truth for AI model availability
Project-URL: Homepage, https://github.com/Venkatesh188/ai-model-registry
Project-URL: Repository, https://github.com/Venkatesh188/ai-model-registry
Project-URL: Documentation, https://github.com/Venkatesh188/ai-model-registry#readme
Author-email: Venkatesh <rajuvenkatesh188@email.com>
License-Expression: MIT
Keywords: ai,anthropic,llm,models,openai,registry
Classifier: Development Status :: 3 - Alpha
Classifier: Intended Audience :: Developers
Classifier: License :: OSI Approved :: MIT License
Classifier: Programming Language :: Python :: 3
Classifier: Programming Language :: Python :: 3.8
Classifier: Programming Language :: Python :: 3.9
Classifier: Programming Language :: Python :: 3.10
Classifier: Programming Language :: Python :: 3.11
Classifier: Programming Language :: Python :: 3.12
Requires-Python: >=3.8
Requires-Dist: fastapi>=0.100.0
Requires-Dist: pydantic>=2.0.0
Requires-Dist: requests>=2.25.0
Requires-Dist: uvicorn>=0.22.0
